client_wd/__init__.py
client_wd/add_contact.py
client_wd/database.py
client_wd/del_contact.py
client_wd/main_window.py
client_wd/main_window_conv.py
client_wd/start_dialog.py
client_wd/transport.py
common/__init__.py
common/decos.py
common/descryptors.py
common/errors.py
common/metaclasses.py
common/utils.py
common/variables.py
logs/__init__.py
logs/config_client_log.py
unit_tests/__init__.py
unit_tests/test_client.py
unit_tests/test_utils.py
mess_clnt-0.1.0.dist-info/METADATA
mess_clnt-0.1.0.dist-info/WHEEL
mess_clnt-0.1.0.dist-info/top_level.txt
mess_clnt-0.1.0.dist-info/RECORD
