Metadata-Version: 2.1
Name: mess-clnt
Version: 0.1.0
Summary: mess_clnt
Home-page: UNKNOWN
Author: android156
Author-email: 4_registrations@mail.ru
License: UNKNOWN
Platform: UNKNOWN
Requires-Dist: PyQt5
Requires-Dist: sqlalchemy
Requires-Dist: pycryptodome
Requires-Dist: pycryptodomex
